timetk/.DS_Store
timetk/__init__.py
timetk-1.0.12.dist-info/WHEEL
timetk-1.0.12.dist-info/METADATA
timetk-1.0.12.dist-info/RECORD
